menousdb/__init__.py
menousdb-0.1.3.dist-info/METADATA
menousdb-0.1.3.dist-info/WHEEL
menousdb-0.1.3.dist-info/top_level.txt
menousdb-0.1.3.dist-info/RECORD
