Metadata-Version: 2.1
Name: menousdb
Version: 0.1.3
Summary: A SDK for Menous DB
Author: Snehashish Laskar
Author-email: snehashish.laskar@gmail.com
License: 
Classifier: Development Status :: 1 - Planning
Classifier: Intended Audience :: Developers
Classifier: Programming Language :: Python :: 3
Classifier: Operating System :: Unix
Classifier: Operating System :: MacOS :: MacOS X
Classifier: Operating System :: Microsoft :: Windows
